ness/__init__.py
ness/app.py
ness/logo.py
ness/cli/__init__.py
ness/cli/arguments.py
ness/commands/__init__.py
ness/commands/build_database.py
ness/commands/build_model.py
ness/commands/search.py
ness/databases/__init__.py
ness/databases/base_database.py
ness/databases/scann_database.py
ness/databases/utils.py
ness/models/__init__.py
ness/models/base_model.py
ness/models/fasttext.py
ness/models/utils.py
ness/models/word2vec.py
ness/utils/__init__.py
ness/utils/fasta.py
ness/utils/iteration.py
ness/utils/ngrams.py
ness/utils/version.py
ness_search-0.0.6.dist-info/LICENSE
ness_search-0.0.6.dist-info/METADATA
ness_search-0.0.6.dist-info/WHEEL
ness_search-0.0.6.dist-info/entry_points.txt
ness_search-0.0.6.dist-info/top_level.txt
ness_search-0.0.6.dist-info/RECORD
