Metadata-Version: 2.1
Name: ness-search
Version: 0.0.6
Summary: NESS: Vector-based Alignment-free Sequence Search
Author: Frederico Schmitt Kremer; Thiago Carvalho
Author-email: fred.s.kremer@gmail.com
Project-URL: Source Code, https://github.com/omixlab/ness
Keywords: bioinformatics machine-learning data science
License-File: LICENSE
Requires-Dist: pandas
Requires-Dist: numpy
Requires-Dist: scipy
Requires-Dist: scikit-learn
Requires-Dist: biopython
Requires-Dist: gensim (>4.0.0)
Requires-Dist: jsonlines
Requires-Dist: scann (==1.2.6)
Requires-Dist: h5py
Requires-Dist: pysam
Requires-Dist: twine
